README.md
setup.py
ddh/embed.py
ddh/level.py
discord_data_helper.egg-info/PKG-INFO
discord_data_helper.egg-info/SOURCES.txt
discord_data_helper.egg-info/dependency_links.txt
discord_data_helper.egg-info/not-zip-safe
discord_data_helper.egg-info/top_level.txt