Metadata-Version: 1.0
Name: discord-data-helper
Version: 0.3.3
Summary: Very simple to use module
Home-page: https://github.com/DDH-MAKER/discord-data-helper
Author: Helloyunho, func
Author-email: rlacks628628@naver.com
License: CCL
Platform: UNKNOWN
